resilient_http/__init__.py
resilient_http/backoff.py
resilient_http/circuit_breaker.py
resilient_http/exceptions.py
resilient_http/metrics.py
resilient_http/resilient_async_client.py
resilient_http/resilient_session.py
resilient_http/retry_policy.py
resilient_http-1.0.12.dist-info/licenses/LICENSE
resilient_http-1.0.12.dist-info/METADATA
resilient_http-1.0.12.dist-info/WHEEL
resilient_http-1.0.12.dist-info/top_level.txt
resilient_http-1.0.12.dist-info/RECORD
