Metadata-Version: 2.4
Name: resilient-http
Version: 1.0.12
Summary: Resilience layer for Python HTTP clients (smart retries, jitter backoff, circuit breaker)
Author: Plamen Nikolov
License-Expression: MIT
Project-URL: Homepage, https://github.com/pgnikolov/resilient-http
Project-URL: Issues, https://github.com/pgnikolov/resilient-http/issues
Classifier: Programming Language :: Python :: 3
Classifier: Operating System :: OS Independent
Requires-Python: >=3.9
License-File: LICENSE
Requires-Dist: requests>=2.28
Requires-Dist: httpx>=0.27
Provides-Extra: dev
Requires-Dist: pytest; extra == "dev"
Requires-Dist: pytest-cov; extra == "dev"
Requires-Dist: pytest-asyncio; extra == "dev"
Requires-Dist: ruff; extra == "dev"
Requires-Dist: black; extra == "dev"
Requires-Dist: mypy; extra == "dev"
Requires-Dist: build; extra == "dev"
Requires-Dist: twine; extra == "dev"
Dynamic: license-file
